{"version": 0.6, "generator": "Overpass API 0.7.56.7 b85c4387", "osm3s": {"timestamp_osm_base": "2020-09-17T06:36:02Z", "copyright": "The data included in this document is from www.openstreetmap.org. The data is made available under ODbL."}, "elements": [{"type": "node", "id": 34828478, "lat": 44.024258, "lon": -116.950401}, {"type": "node", "id": 34829324, "lat": 44.0474041, "lon": -116.9754993}, {"type": "node", "id": 34834333, "lat": 44.0240246, "lon": -116.9502697}, {"type": "node", "id": 34834479, "lat": 44.0474851, "lon": -116.9757139}, {"type": "node", "id": 34835646, "lat": 44.0826162, "lon": -117.0177101}, {"type": "node", "id": 34835710, "lat": 44.0259629, "lon": -116.9485874}, {"type": "node", "id": 34839710, "lat": 44.083185, "lon": -117.017787}, {"type": "node", "id": 34839783, "lat": 44.0256957, "lon": -116.9487609}, {"type": "node", "id": 34842092, "lat": 44.0228313, "lon": -116.9476069}, {"type": "node", "id": 34842824, "lat": 44.0477785, "lon": -116.97679}, {"type": "node", "id": 34844971, "lat": 44.0834984, "lon": -117.0178514}, {"type": "node", "id": 34845051, "lat": 44.026113, "lon": -116.9482464}, {"type": "node", "id": 34850094, "lat": 44.0255684, "lon": -116.9472188}, {"type": "node", "id": 34850377, "lat": 44.0258272, "lon": -116.9471752}, {"type": "node", "id": 34853405, "lat": 44.0260514, "lon": -116.9484396}, {"type": "node", "id": 34856907, "lat": 44.0260787, "lon": -116.9477016}, {"type": "node", "id": 34858622, "lat": 44.0238337, "lon": -116.9498088}, {"type": "node", "id": 34861945, "lat": 44.026131, "lon": -116.9479495}, {"type": "node", "id": 34863238, "lat": 44.0238432, "lon": -116.9496267}, {"type": "node", "id": 34863404, "lat": 44.0257711, "lon": -116.9473108}, {"type": "node", "id": 34869846, "lat": 44.0259568, "lon": -116.9474837}, {"type": "node", "id": 34871615, "lat": 44.0828149, "lon": -117.0176837}, {"type": "node", "id": 34875433, "lat": 44.02332, "lon": -116.9476795}, {"type": "node", "id": 34875756, "lat": 44.0237012, "lon": -116.9499886}, {"type": "node", "id": 34882899, "lat": 44.023955, "lon": -116.9493385}, {"type": "node", "id": 34885614, "lat": 44.0828973, "lon": -117.0165371}, {"type": "node", "id": 34886124, "lat": 44.0509139, "lon": -116.9762823}, {"type": "node", "id": 34889478, "lat": 44.0509096, "lon": -116.9771641}, {"type": "node", "id": 34890446, "lat": 44.0818298, "lon": -117.0136878}, {"type": "node", "id": 34891995, "lat": 44.0263029, "lon": -116.9501375}, {"type": "node", "id": 34893818, "lat": 44.0509774, "lon": -116.9781088}, {"type": "node", "id": 34895109, "lat": 44.0827708, "lon": -117.0137154}, {"type": "node", "id": 34895118, "lat": 44.0510784, "lon": -116.9785589}, {"type": "node", "id": 34899186, "lat": 44.0829782, "lon": -117.0175725}, {"type": "node", "id": 34899497, "lat": 44.0516016, "lon": -116.9796817}, {"type": "node", "id": 34900064, "lat": 44.050087, "lon": -116.9786714}, {"type": "node", "id": 34903920, "lat": 44.0497626, "lon": -116.9783357}, {"type": "node", "id": 34905131, "lat": 44.0262403, "lon": -116.9477208}, {"type": "node", "id": 34928047, "lat": 44.0824451, "lon": -117.0178507}, {"type": "node", "id": 34928230, "lat": 44.0082015, "lon": -116.9419822}, {"type": "node", "id": 34942462, "lat": 44.04943, "lon": -116.9780835}, {"type": "node", "id": 34945480, "lat": 44.0820075, "lon": -117.0145017}, {"type": "node", "id": 34946694, "lat": 44.0131761, "lon": -116.9436285}, {"type": "node", "id": 34951694, "lat": 44.0489937, "lon": -116.9778502}, {"type": "node", "id": 34952598, "lat": 44.0145921, "lon": -116.9437887}, {"type": "node", "id": 34995956, "lat": 44.0135539, "lon": -116.9437479}, {"type": "node", "id": 34997478, "lat": 44.0830319, "lon": -117.0167607}, {"type": "node", "id": 34999109, "lat": 44.0484457, "lon": -116.9776472}, {"type": "node", "id": 34999877, "lat": 44.0170915, "lon": -116.9449981}, {"type": "node", "id": 35007189, "lat": 44.0831439, "lon": -117.0171004}, {"type": "node", "id": 35011619, "lat": 44.0479114, "lon": -116.9771788}, {"type": "node", "id": 35013828, "lat": 44.0242265, "lon": -116.9474059}, {"type": "node", "id": 35015286, "lat": 44.0831015, "lon": -117.0173954}, {"type": "node", "id": 35015880, "lat": 44.0141599, "lon": -116.9438505}, {"type": "node", "id": 35019910, "lat": 44.0478409, "lon": -116.9769839}, {"type": "node", "id": 35022245, "lat": 44.0822772, "lon": -117.0138726}, {"type": "node", "id": 35026833, "lat": 44.0508231, "lon": -116.9759517}, {"type": "node", "id": 35038878, "lat": 44.0820917, "lon": -117.0140267}, {"type": "node", "id": 35048129, "lat": 44.0821575, "lon": -117.0139524}, {"type": "node", "id": 35052434, "lat": 44.0244692, "lon": -116.9504157}, {"type": "node", "id": 35055573, "lat": 44.0265177, "lon": -116.9483125}, {"type": "node", "id": 35059287, "lat": 44.0837258, "lon": -117.0179533}, {"type": "node", "id": 35064500, "lat": 44.0820529, "lon": -117.0140958}, {"type": "node", "id": 35065555, "lat": 44.0468849, "lon": -116.9745235}, {"type": "node", "id": 35066297, "lat": 44.0256198, "lon": -116.9500814}, {"type": "node", "id": 35074555, "lat": 44.0472284, "lon": -116.9750792}, {"type": "node", "id": 35079326, "lat": 44.0820315, "lon": -117.0145861}, {"type": "node", "id": 35088105, "lat": 44.0224676, "lon": -116.9475024}, {"type": "node", "id": 130908199, "lat": 44.025447, "lon": -116.9235507, "tags": {"highway": "traffic_signals"}}, {"type": "node", "id": 130933146, "lat": 43.972476, "lon": -116.914368}, {"type": "node", "id": 130945876, "lat": 43.9413108, "lon": -116.8679394}, {"type": "node", "id": 130982611, "lat": 43.97638, "lon": -116.920022}, {"type": "node", "id": 130983528, "lat": 43.969726, "lon": -116.911888, "tags": {"highway": "motorway_junction", "ref": "3"}}, {"type": "node", "id": 130983531, "lat": 43.970446, "lon": -116.912544}, {"type": "node", "id": 130983534, "lat": 43.970729, "lon": -116.912708}, {"type": "node", "id": 130983537, "lat": 43.970966, "lon": -116.912814}, {"type": "node", "id": 130983541, "lat": 43.971288, "lon": -116.912899}, {"type": "node", "id": 130983543, "lat": 43.97165, "lon": -116.912953}, {"type": "node", "id": 130983545, "lat": 43.971882, "lon": -116.913055}, {"type": "node", "id": 130983547, "lat": 43.972048, "lon": -116.91318}, {"type": "node", "id": 130983550, "lat": 43.972176, "lon": -116.913371}, {"type": "node", "id": 130983556, "lat": 43.972286, "lon": -116.913621}, {"type": "node", "id": 130983561, "lat": 43.972398, "lon": -116.914052}, {"type": "node", "id": 130983564, "lat": 43.972615, "lon": -116.9149128}, {"type": "node", "id": 130983566, "lat": 43.9741445, "lon": -116.9174236}, {"type": "node", "id": 130986170, "lat": 43.9046013, "lon": -116.8130795}, {"type": "node", "id": 131002502, "lat": 43.9961211, "lon": -116.9365663, "tags": {"highway": "motorway_junction", "noref": "yes"}}, {"type": "node", "id": 131002505, "lat": 43.9950444, "lon": -116.9361562}, {"type": "node", "id": 131002508, "lat": 43.9945527, "lon": -116.9360159}, {"type": "node", "id": 131002511, "lat": 43.993406, "lon": -116.935358}, {"type": "node", "id": 131002512, "lat": 43.9925922, "lon": -116.9348186}, {"type": "node", "id": 131002515, "lat": 43.9923941, "lon": -116.9345568}, {"type": "node", "id": 131002517, "lat": 43.9912685, "lon": -116.9336821}, {"type": "node", "id": 131014842, "lat": 43.905109, "lon": -116.8131138, "tags": {"highway": "motorway_junction", "ref": "9"}}, {"type": "node", "id": 131014877, "lat": 43.908512, "lon": -116.817077}, {"type": "node", "id": 131019736, "lat": 43.9683813, "lon": -116.9106956}, {"type": "node", "id": 131019738, "lat": 43.969533, "lon": -116.912391}, {"type": "node", "id": 131019740, "lat": 43.969736, "lon": -116.912776}, {"type": "node", "id": 131019742, "lat": 43.969921, "lon": -116.913307}, {"type": "node", "id": 131019745, "lat": 43.9701254, "lon": -116.9140905}, {"type": "node", "id": 131019748, "lat": 43.970244, "lon": -116.914505}, {"type": "node", "id": 131019751, "lat": 43.970353, "lon": -116.914742}, {"type": "node", "id": 131019755, "lat": 43.970504, "lon": -116.914979}, {"type": "node", "id": 131019758, "lat": 43.97066, "lon": -116.91509}, {"type": "node", "id": 131019760, "lat": 43.970951, "lon": -116.915162}, {"type": "node", "id": 131019763, "lat": 43.971385, "lon": -116.915226}, {"type": "node", "id": 131019766, "lat": 43.971717, "lon": -116.915326}, {"type": "node", "id": 131019769, "lat": 43.972094, "lon": -116.91561}, {"type": "node", "id": 131019772, "lat": 43.972676, "lon": -116.91613, "tags": {"highway": "motorway_junction", "ref": "3"}}, {"type": "node", "id": 131023419, "lat": 43.908639, "lon": -116.817885, "tags": {"highway": "motorway_junction", "ref": "9"}}, {"type": "node", "id": 131055979, "lat": 44.0056779, "lon": -116.9409246}, {"type": "node", "id": 131055985, "lat": 43.9995459, "lon": -116.9382829}, {"type": "node", "id": 131055993, "lat": 43.9964586, "lon": -116.9367326}, {"type": "node", "id": 131055996, "lat": 43.994811, "lon": -116.935841}, {"type": "node", "id": 131056002, "lat": 43.992509, "lon": -116.934483}, {"type": "node", "id": 131056007, "lat": 43.989703, "lon": -116.932624}, {"type": "node", "id": 131056010, "lat": 43.987255, "lon": -116.9308}, {"type": "node", "id": 131056014, "lat": 43.984496, "lon": -116.92862}, {"type": "node", "id": 131056017, "lat": 43.983616, "lon": -116.927863}, {"type": "node", "id": 131056021, "lat": 43.980913, "lon": -116.9253}, {"type": "node", "id": 131056024, "lat": 43.97846, "lon": -116.922851}, {"type": "node", "id": 131056027, "lat": 43.976322, "lon": -116.920508}, {"type": "node", "id": 131056030, "lat": 43.976105, "lon": -116.92027}, {"type": "node", "id": 131056033, "lat": 43.973462, "lon": -116.917112}, {"type": "node", "id": 131056036, "lat": 43.972103, "lon": -116.915415}, {"type": "node", "id": 131056041, "lat": 43.9715461, "lon": -116.9146669}, {"type": "node", "id": 131056045, "lat": 43.9701632, "lon": -116.9129551}, {"type": "node", "id": 131056049, "lat": 43.966751, "lon": -116.908727}, {"type": "node", "id": 131056054, "lat": 43.9652983, "lon": -116.9069056}, {"type": "node", "id": 131056056, "lat": 43.9614656, "lon": -116.9021302}, {"type": "node", "id": 131056058, "lat": 43.959771, "lon": -116.900093}, {"type": "node", "id": 131056060, "lat": 43.959371, "lon": -116.899588}, {"type": "node", "id": 131056062, "lat": 43.95702, "lon": -116.896413}, {"type": "node", "id": 131056064, "lat": 43.955726, "lon": -116.894425}, {"type": "node", "id": 131056066, "lat": 43.954961, "lon": -116.893249}, {"type": "node", "id": 131056069, "lat": 43.954841, "lon": -116.893064}, {"type": "node", "id": 131056073, "lat": 43.953069, "lon": -116.88997}, {"type": "node", "id": 131056076, "lat": 43.952579, "lon": -116.889114}, {"type": "node", "id": 131056079, "lat": 43.950533, "lon": -116.885277}, {"type": "node", "id": 131056082, "lat": 43.948607, "lon": -116.881595}, {"type": "node", "id": 131056085, "lat": 43.946617, "lon": -116.877889}, {"type": "node", "id": 131056099, "lat": 43.942936, "lon": -116.87106}, {"type": "node", "id": 131056102, "lat": 43.9411522, "lon": -116.8676692}, {"type": "node", "id": 131056105, "lat": 43.940545, "lon": -116.866523}, {"type": "node", "id": 131056108, "lat": 43.937527, "lon": -116.860888}, {"type": "node", "id": 131056111, "lat": 43.936157, "lon": -116.858314}, {"type": "node", "id": 131056115, "lat": 43.935803, "lon": -116.857649}, {"type": "node", "id": 131056118, "lat": 43.933917, "lon": -116.854056}, {"type": "node", "id": 131056121, "lat": 43.933477, "lon": -116.853234}, {"type": "node", "id": 131056124, "lat": 43.931976, "lon": -116.850432}, {"type": "node", "id": 131056126, "lat": 43.930961, "lon": -116.848491}, {"type": "node", "id": 131056128, "lat": 43.930046, "lon": -116.846875}, {"type": "node", "id": 131056130, "lat": 43.928556, "lon": -116.844017}, {"type": "node", "id": 131056132, "lat": 43.928226, "lon": -116.843383}, {"type": "node", "id": 131056135, "lat": 43.927318, "lon": -116.841848}, {"type": "node", "id": 131056136, "lat": 43.926395, "lon": -116.840415}, {"type": "node", "id": 131056138, "lat": 43.925873, "lon": -116.83963}, {"type": "node", "id": 131056140, "lat": 43.925234, "lon": -116.838667}, {"type": "node", "id": 131056143, "lat": 43.92411, "lon": -116.837087}, {"type": "node", "id": 131056146, "lat": 43.92289, "lon": -116.835421}, {"type": "node", "id": 131056149, "lat": 43.921549, "lon": -116.833817}, {"type": "node", "id": 131056151, "lat": 43.919069, "lon": -116.830724}, {"type": "node", "id": 131056154, "lat": 43.918914, "lon": -116.830533}, {"type": "node", "id": 131056156, "lat": 43.917728, "lon": -116.829074}, {"type": "node", "id": 131056158, "lat": 43.91649, "lon": -116.82753}, {"type": "node", "id": 131056160, "lat": 43.915252, "lon": -116.826042}, {"type": "node", "id": 131056163, "lat": 43.913825, "lon": -116.824279}, {"type": "node", "id": 131056166, "lat": 43.912933, "lon": -116.823177}, {"type": "node", "id": 131056169, "lat": 43.911705, "lon": -116.821631}, {"type": "node", "id": 131056173, "lat": 43.910457, "lon": -116.82006}, {"type": "node", "id": 131056176, "lat": 43.909211, "lon": -116.818608}, {"type": "node", "id": 131056179, "lat": 43.907451, "lon": -116.816374}, {"type": "node", "id": 131056182, "lat": 43.906896, "lon": -116.815668}, {"type": "node", "id": 131056185, "lat": 43.906, "lon": -116.81467}, {"type": "node", "id": 131056459, "lat": 44.0083713, "lon": -116.941655}, {"type": "node", "id": 131056468, "lat": 44.0058505, "lon": -116.9405999}, {"type": "node", "id": 131056471, "lat": 44.0009702, "lon": -116.9384884}, {"type": "node", "id": 131056477, "lat": 43.9996368, "lon": -116.937894}, {"type": "node", "id": 131056478, "lat": 43.9985955, "lon": -116.937382}, {"type": "node", "id": 131056482, "lat": 43.9952532, "lon": -116.9356551}, {"type": "node", "id": 131056488, "lat": 43.9935802, "lon": -116.9347011}, {"type": "node", "id": 131056491, "lat": 43.9923439, "lon": -116.9339101}, {"type": "node", "id": 131056498, "lat": 43.9906066, "lon": -116.9327755}, {"type": "node", "id": 131056501, "lat": 43.988681, "lon": -116.931396}, {"type": "node", "id": 131056517, "lat": 43.986504, "lon": -116.929745}, {"type": "node", "id": 131056525, "lat": 43.9838031, "lon": -116.9275117}, {"type": "node", "id": 131056529, "lat": 43.981301, "lon": -116.92518}, {"type": "node", "id": 131056533, "lat": 43.9774072, "lon": -116.9212289}, {"type": "node", "id": 131056535, "lat": 43.975449, "lon": -116.918982}, {"type": "node", "id": 131056539, "lat": 43.97229, "lon": -116.915065}, {"type": "node", "id": 131056541, "lat": 43.972215, "lon": -116.914977}, {"type": "node", "id": 131056545, "lat": 43.970761, "lon": -116.913196}, {"type": "node", "id": 131056547, "lat": 43.970372, "lon": -116.912704}, {"type": "node", "id": 131056549, "lat": 43.968245, "lon": -116.9100749}, {"type": "node", "id": 131056555, "lat": 43.9668108, "lon": -116.9082636}, {"type": "node", "id": 131056559, "lat": 43.9654685, "lon": -116.9065572}, {"type": "node", "id": 131056563, "lat": 43.9633916, "lon": -116.9039976}, {"type": "node", "id": 131056566, "lat": 43.9617654, "lon": -116.9020087}, {"type": "node", "id": 131056569, "lat": 43.9594451, "lon": -116.8991151}, {"type": "node", "id": 131056575, "lat": 43.95821, "lon": -116.897508}, {"type": "node", "id": 131056577, "lat": 43.956372, "lon": -116.894887}, {"type": "node", "id": 131056580, "lat": 43.955926, "lon": -116.894175}, {"type": "node", "id": 131056583, "lat": 43.955209, "lon": -116.89303}, {"type": "node", "id": 131056587, "lat": 43.955021, "lon": -116.89273}, {"type": "node", "id": 131056590, "lat": 43.953415, "lon": -116.890014}, {"type": "node", "id": 131056592, "lat": 43.953407, "lon": -116.890001}, {"type": "node", "id": 131056594, "lat": 43.951935, "lon": -116.887284}, {"type": "node", "id": 131056597, "lat": 43.946491, "lon": -116.877007}, {"type": "node", "id": 131056600, "lat": 43.945395, "lon": -116.875011}, {"type": "node", "id": 131056611, "lat": 43.943166, "lon": -116.870759}, {"type": "node", "id": 131056615, "lat": 43.942099, "lon": -116.868869}, {"type": "node", "id": 131056619, "lat": 43.9415348, "lon": -116.8677358}, {"type": "node", "id": 131056621, "lat": 43.9413924, "lon": -116.8674813}, {"type": "node", "id": 131056624, "lat": 43.940384, "lon": -116.86553}, {"type": "node", "id": 131056627, "lat": 43.938891, "lon": -116.862737}, {"type": "node", "id": 131056630, "lat": 43.937606, "lon": -116.860277}, {"type": "node", "id": 131056633, "lat": 43.936621, "lon": -116.858472}, {"type": "node", "id": 131056636, "lat": 43.936555, "lon": -116.858351}, {"type": "node", "id": 131056639, "lat": 43.935661, "lon": -116.856617}, {"type": "node", "id": 131056642, "lat": 43.933855, "lon": -116.85325}, {"type": "node", "id": 131056646, "lat": 43.931633, "lon": -116.849109}, {"type": "node", "id": 131056649, "lat": 43.930642, "lon": -116.84719}, {"type": "node", "id": 131056652, "lat": 43.929959, "lon": -116.845962}, {"type": "node", "id": 131056655, "lat": 43.928809, "lon": -116.843829}, {"type": "node", "id": 131056657, "lat": 43.928214, "lon": -116.842727}, {"type": "node", "id": 131056659, "lat": 43.927868, "lon": -116.842158}, {"type": "node", "id": 131056662, "lat": 43.927145, "lon": -116.840893}, {"type": "node", "id": 131056664, "lat": 43.926124, "lon": -116.839361}, {"type": "node", "id": 131056666, "lat": 43.925196, "lon": -116.83797}, {"type": "node", "id": 131056669, "lat": 43.924315, "lon": -116.836719}, {"type": "node", "id": 131056672, "lat": 43.923794, "lon": -116.836025}, {"type": "node", "id": 131056675, "lat": 43.922662, "lon": -116.834641}, {"type": "node", "id": 131056678, "lat": 43.92157, "lon": -116.833228}, {"type": "node", "id": 131056681, "lat": 43.920451, "lon": -116.831867}, {"type": "node", "id": 131056683, "lat": 43.919123, "lon": -116.83022}, {"type": "node", "id": 131056685, "lat": 43.914218, "lon": -116.824135}, {"type": "node", "id": 131056687, "lat": 43.913227, "lon": -116.822906}, {"type": "node", "id": 131056689, "lat": 43.912162, "lon": -116.821617}, {"type": "node", "id": 131056691, "lat": 43.912098, "lon": -116.82154}, {"type": "node", "id": 131056692, "lat": 43.90784, "lon": -116.816246}, {"type": "node", "id": 131056693, "lat": 43.907654, "lon": -116.816023}, {"type": "node", "id": 131056694, "lat": 43.906358, "lon": -116.814451}, {"type": "node", "id": 131056695, "lat": 43.906262, "lon": -116.814344}, {"type": "node", "id": 260099965, "lat": 43.998455, "lon": -116.9377719}, {"type": "node", "id": 660561695, "lat": 44.0241637, "lon": -116.949164}, {"type": "node", "id": 660561699, "lat": 44.024446, "lon": -116.9491412}, {"type": "node", "id": 765967800, "lat": 44.010935, "lon": -116.9427601}, {"type": "node", "id": 765967802, "lat": 44.012008, "lon": -116.9432164, "tags": {"highway": "motorway_junction", "noref": "yes"}}, {"type": "node", "id": 765967819, "lat": 44.0109003, "lon": -116.9431463}, {"type": "node", "id": 765967820, "lat": 44.0128641, "lon": -116.9439805}, {"type": "node", "id": 765967821, "lat": 44.0140926, "lon": -116.9444876}, {"type": "node", "id": 765967822, "lat": 44.0170477, "lon": -116.9457966}, {"type": "node", "id": 765967833, "lat": 44.0199772, "lon": -116.9470286}, {"type": "node", "id": 765967844, "lat": 44.0214851, "lon": -116.9476846}, {"type": "node", "id": 765967845, "lat": 44.0237157, "lon": -116.9486136}, {"type": "node", "id": 765967861, "lat": 44.0249324, "lon": -116.9491708}, {"type": "node", "id": 765981043, "lat": 44.0247398, "lon": -116.9504689}, {"type": "node", "id": 765981046, "lat": 44.0251326, "lon": -116.9502316}, {"type": "node", "id": 765981050, "lat": 44.0249441, "lon": -116.9469854}, {"type": "node", "id": 765981052, "lat": 44.0255786, "lon": -116.9470338}, {"type": "node", "id": 765981070, "lat": 44.0243193, "lon": -116.9505666}, {"type": "node", "id": 765981071, "lat": 44.0240358, "lon": -116.9504406}, {"type": "node", "id": 765981072, "lat": 44.023949, "lon": -116.9503534}, {"type": "node", "id": 765981073, "lat": 44.0238526, "lon": -116.9502421}, {"type": "node", "id": 765981075, "lat": 44.0233222, "lon": -116.9492014}, {"type": "node", "id": 765981076, "lat": 44.02303, "lon": -116.9487642}, {"type": "node", "id": 765981077, "lat": 44.0226915, "lon": -116.9484182}, {"type": "node", "id": 765981078, "lat": 44.02257, "lon": -116.948331}, {"type": "node", "id": 765981080, "lat": 44.0262055, "lon": -116.9496989, "tags": {"highway": "motorway_junction", "ref": "376B"}}, {"type": "node", "id": 765981081, "lat": 44.0250635, "lon": -116.9493263}, {"type": "node", "id": 765981114, "lat": 44.023366, "lon": -116.9480725, "tags": {"highway": "motorway_junction", "ref": "376A"}}, {"type": "node", "id": 765981120, "lat": 44.0244387, "lon": -116.9484358}, {"type": "node", "id": 765981127, "lat": 44.0251754, "lon": -116.9486826}, {"type": "node", "id": 765981131, "lat": 44.0255548, "lon": -116.9487698}, {"type": "node", "id": 765981150, "lat": 44.0171528, "lon": -116.9450933}, {"type": "node", "id": 765981152, "lat": 44.017202, "lon": -116.9451631}, {"type": "node", "id": 765981153, "lat": 44.0175212, "lon": -116.945421}, {"type": "node", "id": 765981155, "lat": 44.0180572, "lon": -116.9457036}, {"type": "node", "id": 765981156, "lat": 44.018857, "lon": -116.946097}, {"type": "node", "id": 765981301, "lat": 44.0210079, "lon": -116.9470371, "tags": {"highway": "motorway_junction", "ref": "376B"}}, {"type": "node", "id": 765981320, "lat": 44.0237328, "lon": -116.9476473}, {"type": "node", "id": 765981324, "lat": 44.0239912, "lon": -116.94754}, {"type": "node", "id": 765981331, "lat": 44.0245621, "lon": -116.9471698}, {"type": "node", "id": 766012047, "lat": 44.0824165, "lon": -117.0156829}, {"type": "node", "id": 766012085, "lat": 44.0849099, "lon": -117.0191694, "tags": {"highway": "motorway_junction", "ref": "371"}}, {"type": "node", "id": 766012088, "lat": 44.084246, "lon": -117.0184576}, {"type": "node", "id": 766012089, "lat": 44.0839647, "lon": -117.0181625}, {"type": "node", "id": 766012094, "lat": 44.0827239, "lon": -117.0178031}, {"type": "node", "id": 766012305, "lat": 44.0820765, "lon": -117.014681}, {"type": "node", "id": 766012306, "lat": 44.082458, "lon": -117.0152658}, {"type": "node", "id": 766012308, "lat": 44.0829589, "lon": -117.0160168}, {"type": "node", "id": 766012354, "lat": 44.0820717, "lon": -117.0137398}, {"type": "node", "id": 766012360, "lat": 44.0813952, "lon": -117.0134896}, {"type": "node", "id": 766012364, "lat": 44.0812267, "lon": -117.0133633}, {"type": "node", "id": 766012367, "lat": 44.081043, "lon": -117.0131803}, {"type": "node", "id": 766012369, "lat": 44.0806497, "lon": -117.0127451}, {"type": "node", "id": 766012370, "lat": 44.0801716, "lon": -117.0122111, "tags": {"highway": "motorway_junction", "ref": "371"}}, {"type": "node", "id": 766012583, "lat": 44.0508665, "lon": -116.9794261, "tags": {"highway": "motorway_junction", "ref": "374"}}, {"type": "node", "id": 766012587, "lat": 44.0504387, "lon": -116.979045}, {"type": "node", "id": 766012632, "lat": 44.0461548, "lon": -116.9733965}, {"type": "node", "id": 766012941, "lat": 44.0462744, "lon": -116.9731712}, {"type": "node", "id": 766012971, "lat": 44.0526158, "lon": -116.9812262}, {"type": "node", "id": 766012981, "lat": 44.0293528, "lon": -116.9506498}, {"type": "node", "id": 766012982, "lat": 44.029827, "lon": -116.9508498}, {"type": "node", "id": 766012983, "lat": 44.0306176, "lon": -116.9512307}, {"type": "node", "id": 766012984, "lat": 44.0310843, "lon": -116.9514936}, {"type": "node", "id": 766012985, "lat": 44.0316611, "lon": -116.9518818}, {"type": "node", "id": 766012986, "lat": 44.032512, "lon": -116.9526291}, {"type": "node", "id": 766012988, "lat": 44.0340991, "lon": -116.9546129}, {"type": "node", "id": 766012989, "lat": 44.0343691, "lon": -116.9550719}, {"type": "node", "id": 766012990, "lat": 44.0357326, "lon": -116.9577803}, {"type": "node", "id": 766012991, "lat": 44.0378372, "lon": -116.9620561}, {"type": "node", "id": 766012992, "lat": 44.0384812, "lon": -116.9631236}, {"type": "node", "id": 766012995, "lat": 44.0401356, "lon": -116.9653767}, {"type": "node", "id": 766012997, "lat": 44.0423567, "lon": -116.9681876}, {"type": "node", "id": 766012999, "lat": 44.0477087, "lon": -116.9750326}, {"type": "node", "id": 766013002, "lat": 44.0484089, "lon": -116.9758473, "tags": {"highway": "motorway_junction", "ref": "374"}}, {"type": "node", "id": 766013003, "lat": 44.0529766, "lon": -116.9817017}, {"type": "node", "id": 766013004, "lat": 44.0595369, "lon": -116.9901013}, {"type": "node", "id": 766013005, "lat": 44.0606664, "lon": -116.9914638}, {"type": "node", "id": 766013006, "lat": 44.0614181, "lon": -116.992188}, {"type": "node", "id": 766013008, "lat": 44.0623047, "lon": -116.9929766}, {"type": "node", "id": 766013009, "lat": 44.0633799, "lon": -116.9937759}, {"type": "node", "id": 766013010, "lat": 44.0646176, "lon": -116.9945216}, {"type": "node", "id": 766013011, "lat": 44.0665564, "lon": -116.995632}, {"type": "node", "id": 766013012, "lat": 44.0678862, "lon": -116.9965118}, {"type": "node", "id": 766013013, "lat": 44.0690772, "lon": -116.9974827}, {"type": "node", "id": 766013015, "lat": 44.0698712, "lon": -116.9982552}, {"type": "node", "id": 766013016, "lat": 44.0708695, "lon": -116.9993764}, {"type": "node", "id": 766013017, "lat": 44.0719255, "lon": -117.0007496}, {"type": "node", "id": 766013018, "lat": 44.0731974, "lon": -117.0025092}, {"type": "node", "id": 766013020, "lat": 44.074976, "lon": -117.0050509}, {"type": "node", "id": 766013021, "lat": 44.080643, "lon": -117.0128679}, {"type": "node", "id": 766013022, "lat": 44.0840649, "lon": -117.0176368}, {"type": "node", "id": 766013023, "lat": 44.0894632, "lon": -117.0249271}, {"type": "node", "id": 766013024, "lat": 44.0925494, "lon": -117.0291328}, {"type": "node", "id": 766013025, "lat": 44.0982251, "lon": -117.0368669}, {"type": "node", "id": 766013026, "lat": 44.1142329, "lon": -117.0592862}, {"type": "node", "id": 766013027, "lat": 44.1167979, "lon": -117.0628911}, {"type": "node", "id": 766013029, "lat": 44.1180688, "lon": -117.0648598}, {"type": "node", "id": 766013030, "lat": 44.1191586, "lon": -117.0667588}, {"type": "node", "id": 766013032, "lat": 44.1205026, "lon": -117.0698541}, {"type": "node", "id": 766013034, "lat": 44.1217734, "lon": -117.0727562}, {"type": "node", "id": 766013035, "lat": 44.125089, "lon": -117.0795369}, {"type": "node", "id": 766013036, "lat": 44.1264868, "lon": -117.0820206}, {"type": "node", "id": 766013037, "lat": 44.1278075, "lon": -117.0841932}, {"type": "node", "id": 766013039, "lat": 44.1299792, "lon": -117.0875996}, {"type": "node", "id": 766013040, "lat": 44.1324819, "lon": -117.0912045}, {"type": "node", "id": 766013041, "lat": 44.1361317, "lon": -117.0960003}, {"type": "node", "id": 766013042, "lat": 44.1378488, "lon": -117.0980709}, {"type": "node", "id": 766013043, "lat": 44.1409633, "lon": -117.1014827}, {"type": "node", "id": 766013045, "lat": 44.147134, "lon": -117.1073031}, {"type": "node", "id": 766013047, "lat": 44.1519068, "lon": -117.1109455}, {"type": "node", "id": 766013049, "lat": 44.1538813, "lon": -117.1123886}, {"type": "node", "id": 766013050, "lat": 44.1577608, "lon": -117.115119}, {"type": "node", "id": 766013053, "lat": 44.1592232, "lon": -117.1159559}, {"type": "node", "id": 766013054, "lat": 44.1603547, "lon": -117.1164923}, {"type": "node", "id": 766013055, "lat": 44.1621172, "lon": -117.1171897}, {"type": "node", "id": 766013056, "lat": 44.1627868, "lon": -117.1175652}, {"type": "node", "id": 766013058, "lat": 44.1632486, "lon": -117.1178978}, {"type": "node", "id": 766013059, "lat": 44.1640413, "lon": -117.1186381}, {"type": "node", "id": 766013062, "lat": 44.1693207, "lon": -117.1260625}, {"type": "node", "id": 766013064, "lat": 44.1707598, "lon": -117.1281653}, {"type": "node", "id": 766013068, "lat": 44.172145, "lon": -117.1301394}, {"type": "node", "id": 766013069, "lat": 44.1729222, "lon": -117.1312016}, {"type": "node", "id": 766013070, "lat": 44.173761, "lon": -117.1321564}, {"type": "node", "id": 766013071, "lat": 44.1749075, "lon": -117.1330791}, {"type": "node", "id": 766013072, "lat": 44.1756616, "lon": -117.1334975}, {"type": "node", "id": 766013073, "lat": 44.1769235, "lon": -117.1341198}, {"type": "node", "id": 766013074, "lat": 44.1777699, "lon": -117.1343773}, {"type": "node", "id": 766013075, "lat": 44.1798628, "lon": -117.134903, "tags": {"highway": "motorway_junction", "ref": "362"}}, {"type": "node", "id": 766013296, "lat": 44.1796166, "lon": -117.1353965}, {"type": "node", "id": 766013297, "lat": 44.1779161, "lon": -117.1349567}, {"type": "node", "id": 766013298, "lat": 44.1768928, "lon": -117.1345811}, {"type": "node", "id": 766013299, "lat": 44.1755693, "lon": -117.1338623}, {"type": "node", "id": 766013300, "lat": 44.1747613, "lon": -117.1333581}, {"type": "node", "id": 766013301, "lat": 44.1733069, "lon": -117.1321242}, {"type": "node", "id": 766013302, "lat": 44.1728293, "lon": -117.1315941}, {"type": "node", "id": 766013303, "lat": 44.1719603, "lon": -117.1306008}, {"type": "node", "id": 766013304, "lat": 44.1705751, "lon": -117.1285623}, {"type": "node", "id": 766013305, "lat": 44.1692592, "lon": -117.1266633}, {"type": "node", "id": 766013310, "lat": 44.1638181, "lon": -117.1190351}, {"type": "node", "id": 766013311, "lat": 44.1631331, "lon": -117.1183591}, {"type": "node", "id": 766013313, "lat": 44.1625624, "lon": -117.1180156}, {"type": "node", "id": 766013314, "lat": 44.1620402, "lon": -117.1176725}, {"type": "node", "id": 766013316, "lat": 44.1602575, "lon": -117.1170105}, {"type": "node", "id": 766013317, "lat": 44.1590847, "lon": -117.1164494}, {"type": "node", "id": 766013319, "lat": 44.15768, "lon": -117.1156018}, {"type": "node", "id": 766013320, "lat": 44.1537389, "lon": -117.1128284}, {"type": "node", "id": 766013322, "lat": 44.1517606, "lon": -117.1113908}, {"type": "node", "id": 766013324, "lat": 44.1469646, "lon": -117.1077215}, {"type": "node", "id": 766013326, "lat": 44.1407785, "lon": -117.1019548}, {"type": "node", "id": 766013327, "lat": 44.1375793, "lon": -117.0985323}, {"type": "node", "id": 766013328, "lat": 44.135843, "lon": -117.096467}, {"type": "node", "id": 766013329, "lat": 44.1321584, "lon": -117.0916926}, {"type": "node", "id": 766013330, "lat": 44.1296596, "lon": -117.0881038}, {"type": "node", "id": 766013331, "lat": 44.1274725, "lon": -117.0846545}, {"type": "node", "id": 766013332, "lat": 44.1261441, "lon": -117.0824229}, {"type": "node", "id": 766013334, "lat": 44.1247424, "lon": -117.0798909}, {"type": "node", "id": 766013335, "lat": 44.1214538, "lon": -117.0730513}, {"type": "node", "id": 766013337, "lat": 44.1201792, "lon": -117.0700901}, {"type": "node", "id": 766013338, "lat": 44.1188659, "lon": -117.0670592}, {"type": "node", "id": 766013340, "lat": 44.1177645, "lon": -117.0651817}, {"type": "node", "id": 766013342, "lat": 44.1165283, "lon": -117.0632398}, {"type": "node", "id": 766013344, "lat": 44.1139594, "lon": -117.0596241}, {"type": "node", "id": 766013347, "lat": 44.0980043, "lon": -117.0373025}, {"type": "node", "id": 766013349, "lat": 44.0923051, "lon": -117.0294936}, {"type": "node", "id": 766013350, "lat": 44.0892474, "lon": -117.0252007}, {"type": "node", "id": 766013352, "lat": 44.0828009, "lon": -117.0162099}, {"type": "node", "id": 766013354, "lat": 44.0805428, "lon": -117.0131146}, {"type": "node", "id": 766013357, "lat": 44.0748723, "lon": -117.0052829}, {"type": "node", "id": 766013360, "lat": 44.0730625, "lon": -117.0026808}, {"type": "node", "id": 766013363, "lat": 44.0718099, "lon": -117.0009106}, {"type": "node", "id": 766013372, "lat": 44.070696, "lon": -116.9994622}, {"type": "node", "id": 766013373, "lat": 44.0697903, "lon": -116.9984698}, {"type": "node", "id": 766013374, "lat": 44.0689385, "lon": -116.9976651}, {"type": "node", "id": 766013376, "lat": 44.0677783, "lon": -116.9966995}, {"type": "node", "id": 766013377, "lat": 44.0664678, "lon": -116.9958627}, {"type": "node", "id": 766013379, "lat": 44.0646021, "lon": -116.9948112}, {"type": "node", "id": 766013382, "lat": 44.0632901, "lon": -116.9940441}, {"type": "node", "id": 766013384, "lat": 44.0621891, "lon": -116.9931858}, {"type": "node", "id": 766013389, "lat": 44.0613102, "lon": -116.9924133}, {"type": "node", "id": 766013391, "lat": 44.0605546, "lon": -116.991657}, {"type": "node", "id": 766013396, "lat": 44.0594367, "lon": -116.9903105}, {"type": "node", "id": 766013399, "lat": 44.0530178, "lon": -116.9821941}, {"type": "node", "id": 766013406, "lat": 44.0484837, "lon": -116.9763898}, {"type": "node", "id": 766013411, "lat": 44.0475853, "lon": -116.9752311}, {"type": "node", "id": 766013416, "lat": 44.0421909, "lon": -116.9683647}, {"type": "node", "id": 766013420, "lat": 44.0399929, "lon": -116.9655805}, {"type": "node", "id": 766013423, "lat": 44.0383077, "lon": -116.9633006}, {"type": "node", "id": 766013426, "lat": 44.0376637, "lon": -116.9621956}, {"type": "node", "id": 766013430, "lat": 44.0355417, "lon": -116.9578751}, {"type": "node", "id": 766013433, "lat": 44.0341973, "lon": -116.9552426}, {"type": "node", "id": 766013436, "lat": 44.0339464, "lon": -116.9548216}, {"type": "node", "id": 766013439, "lat": 44.0329356, "lon": -116.9534838}, {"type": "node", "id": 766013445, "lat": 44.0316066, "lon": -116.9522422}, {"type": "node", "id": 766013447, "lat": 44.0310171, "lon": -116.9518259}, {"type": "node", "id": 766013455, "lat": 44.0293451, "lon": -116.9510159, "tags": {"highway": "motorway_junction", "ref": "376A"}}, {"type": "node", "id": 766013656, "lat": 44.0267435, "lon": -116.9487709}, {"type": "node", "id": 766013657, "lat": 44.0272546, "lon": -116.9494978}, {"type": "node", "id": 766013658, "lat": 44.0275591, "lon": -116.9497126}, {"type": "node", "id": 766013935, "lat": 44.024911, "lon": -116.9472313, "tags": {"crossing": "traffic_signals", "highway": "crossing"}}, {"type": "node", "id": 766017840, "lat": 44.1453864, "lon": -117.1057528}, {"type": "node", "id": 766017843, "lat": 44.1485004, "lon": -117.1084242}, {"type": "node", "id": 766017845, "lat": 44.1500324, "lon": -117.1095669}, {"type": "node", "id": 766017936, "lat": 44.1498746, "lon": -117.1100121}, {"type": "node", "id": 766017937, "lat": 44.1483542, "lon": -117.1088695}, {"type": "node", "id": 766017938, "lat": 44.1452324, "lon": -117.1062087}, {"type": "node", "id": 766047576, "lat": 44.166558, "lon": -117.1222859}, {"type": "node", "id": 766048139, "lat": 44.1662963, "lon": -117.1225112}, {"type": "node", "id": 1072088671, "lat": 44.1823305, "lon": -117.1355618}, {"type": "node", "id": 1072088672, "lat": 44.1822578, "lon": -117.1360788}, {"type": "node", "id": 1072092921, "lat": 44.0976121, "lon": -117.0367651}, {"type": "node", "id": 1072092923, "lat": 44.0979289, "lon": -117.0364633}, {"type": "node", "id": 1072092925, "lat": 44.0976602, "lon": -117.0360971}, {"type": "node", "id": 1072092927, "lat": 44.0973712, "lon": -117.036435}, {"type": "node", "id": 1072097053, "lat": 44.0753623, "lon": -117.0055936}, {"type": "node", "id": 1072097055, "lat": 44.075177, "lon": -117.0056965}, {"type": "node", "id": 1072117320, "lat": 44.0508231, "lon": -116.9764619}, {"type": "node", "id": 1072117325, "lat": 44.0507454, "lon": -116.9772129}, {"type": "node", "id": 1072117330, "lat": 44.0505355, "lon": -116.9775126}, {"type": "node", "id": 1072117331, "lat": 44.0507945, "lon": -116.9770024}, {"type": "node", "id": 1072117334, "lat": 44.0501129, "lon": -116.9775581}, {"type": "node", "id": 1072117335, "lat": 44.0497735, "lon": -116.9772888}, {"type": "node", "id": 1072148252, "lat": 44.0360817, "lon": -116.9584858}, {"type": "node", "id": 1072148253, "lat": 44.0359181, "lon": -116.9586565}, {"type": "node", "id": 1306389683, "lat": 44.0247965, "lon": -116.9470246}, {"type": "node", "id": 1306389685, "lat": 44.0247047, "lon": -116.9470762}, {"type": "node", "id": 1306389687, "lat": 44.0247937, "lon": -116.9475841}, {"type": "node", "id": 1306389690, "lat": 44.0247283, "lon": -116.9501388}, {"type": "node", "id": 1306389694, "lat": 44.02483, "lon": -116.9504129}, {"type": "node", "id": 1735849024, "lat": 43.9791923, "lon": -116.9235994}, {"type": "node", "id": 1735849028, "lat": 43.9850647, "lon": -116.9286001}, {"type": "node", "id": 1735849032, "lat": 43.9790748, "lon": -116.9234844}, {"type": "node", "id": 1735849068, "lat": 44.0033439, "lon": -116.9399137}, {"type": "node", "id": 1735849090, "lat": 43.9771485, "lon": -116.9214459}, {"type": "node", "id": 1735849117, "lat": 43.9792539, "lon": -116.9231742}, {"type": "node", "id": 1735849119, "lat": 43.9793562, "lon": -116.9232797}, {"type": "node", "id": 1735849124, "lat": 43.9966344, "lon": -116.9364196}, {"type": "node", "id": 1735849127, "lat": 44.0008429, "lon": -116.938873}, {"type": "node", "id": 1735849183, "lat": 43.9935131, "lon": -116.9350948}, {"type": "node", "id": 1735849195, "lat": 43.9728819, "lon": -116.9155614}, {"type": "node", "id": 1735849197, "lat": 43.9631389, "lon": -116.9041939}, {"type": "node", "id": 1735849220, "lat": 44.003439, "lon": -116.9395511}, {"type": "node", "id": 1895589750, "lat": 43.9041396, "lon": -116.8126313}, {"type": "node", "id": 2457400770, "lat": 44.0254485, "lon": -116.9234016, "tags": {"highway": "traffic_signals"}}, {"type": "node", "id": 2740906772, "lat": 44.081614, "lon": -117.0136125}, {"type": "node", "id": 2740906779, "lat": 44.0819954, "lon": -117.0143433}, {"type": "node", "id": 2740906781, "lat": 44.0819954, "lon": -117.014416}, {"type": "node", "id": 2740906782, "lat": 44.0820032, "lon": -117.0142559}, {"type": "node", "id": 2740906784, "lat": 44.0820243, "lon": -117.0141702}, {"type": "node", "id": 2740906791, "lat": 44.0822775, "lon": -117.0137493}, {"type": "node", "id": 2740906795, "lat": 44.0824205, "lon": -117.0137813}, {"type": "node", "id": 2825150789, "lat": 44.0067677, "lon": -116.9413885, "tags": {"name": "the Idaho State Line", "note": "This named point on I 84 is used by some traffic information systems."}}, {"type": "node", "id": 2825150790, "lat": 44.006977, "lon": -116.9410787, "tags": {"name": "the Idaho State Line", "note": "This named point on I 84 is used by some traffic information systems."}}, {"type": "node", "id": 2825150791, "lat": 44.0067397, "lon": -116.9413764, "tags": {"name": "the Oregon State Line", "note": "This named point on I 84 is used by some traffic information systems."}}, {"type": "node", "id": 2825150792, "lat": 44.0069524, "lon": -116.9410686, "tags": {"name": "the Oregon State Line", "note": "This named point on I 84 is used by some traffic information systems."}}, {"type": "node", "id": 3356376727, "lat": 43.9947921, "lon": -116.9360842}, {"type": "node", "id": 3356376728, "lat": 43.9946235, "lon": -116.9361241}, {"type": "node", "id": 3356376729, "lat": 43.9945251, "lon": -116.9361643}, {"type": "node", "id": 3356376730, "lat": 43.9943746, "lon": -116.9361965}, {"type": "node", "id": 3356376740, "lat": 43.9924075, "lon": -116.9345745}, {"type": "node", "id": 3996647195, "lat": 44.0482249, "lon": -116.97756}, {"type": "node", "id": 3996647196, "lat": 44.0480436, "lon": -116.9774045}, {"type": "node", "id": 3996647198, "lat": 44.0502588, "lon": -116.9775998}, {"type": "node", "id": 3996647199, "lat": 44.0513262, "lon": -116.9792133}, {"type": "node", "id": 3996647200, "lat": 44.0538127, "lon": -116.9827721}, {"type": "node", "id": 3996647201, "lat": 44.0538723, "lon": -116.9832746}, {"type": "node", "id": 3997842182, "lat": 44.0238623, "lon": -116.9500099}, {"type": "node", "id": 3997842183, "lat": 44.0239362, "lon": -116.9501639}, {"type": "node", "id": 3997842184, "lat": 44.0241452, "lon": -116.9503551}, {"type": "node", "id": 3997842185, "lat": 44.0240614, "lon": -116.9492247}, {"type": "node", "id": 3997842186, "lat": 44.0243014, "lon": -116.9491317}, {"type": "node", "id": 3997842187, "lat": 44.0250842, "lon": -116.9471612}, {"type": "node", "id": 3997842188, "lat": 44.0252478, "lon": -116.9471593}, {"type": "node", "id": 3997842189, "lat": 44.0251293, "lon": -116.9469782}, {"type": "node", "id": 3997842190, "lat": 44.0253364, "lon": -116.9469777}, {"type": "node", "id": 3997842191, "lat": 44.0256695, "lon": -116.94726}, {"type": "node", "id": 3997842192, "lat": 44.0261098, "lon": -116.9478162}, {"type": "node", "id": 3997842193, "lat": 44.0261312, "lon": -116.948095}, {"type": "node", "id": 3997842194, "lat": 44.0261378, "lon": -116.9475263}, {"type": "node", "id": 3997842195, "lat": 44.0260353, "lon": -116.9473838}, {"type": "node", "id": 3997842196, "lat": 44.0259219, "lon": -116.9472499}, {"type": "node", "id": 3997842197, "lat": 44.0257013, "lon": -116.9470922}, {"type": "node", "id": 3997842198, "lat": 44.0254591, "lon": -116.9469971}, {"type": "node", "id": 3997917517, "lat": 44.0137461, "lon": -116.943798}, {"type": "node", "id": 3997917518, "lat": 44.013959, "lon": -116.9438314}, {"type": "node", "id": 3997917519, "lat": 44.0143213, "lon": -116.9438386}, {"type": "node", "id": 3997917520, "lat": 44.0144655, "lon": -116.9438147}, {"type": "node", "id": 4966125929, "lat": 44.0487797, "lon": -116.9762191}, {"type": "node", "id": 4966125930, "lat": 44.0495022, "lon": -116.9769967}, {"type": "node", "id": 4966125931, "lat": 44.0499493, "lon": -116.9774557}, {"type": "node", "id": 4966125932, "lat": 44.0503923, "lon": -116.9775903}, {"type": "node", "id": 4966125933, "lat": 44.0506541, "lon": -116.9773874}, {"type": "node", "id": 4966125934, "lat": 44.0508176, "lon": -116.9767615}, {"type": "node", "id": 4966861906, "lat": 44.0477107, "lon": -116.9765473}, {"type": "node", "id": 4966862517, "lat": 44.0509265, "lon": -116.9776851}, {"type": "node", "id": 4966862518, "lat": 44.0509091, "lon": -116.976749}, {"type": "node", "id": 4966862519, "lat": 44.0504127, "lon": -116.9759921}, {"type": "node", "id": 4966862520, "lat": 44.050511, "lon": -116.976002}, {"type": "node", "id": 4966862521, "lat": 44.0505698, "lon": -116.9760074}, {"type": "node", "id": 4966862522, "lat": 44.0506335, "lon": -116.9760221}, {"type": "node", "id": 4966862523, "lat": 44.0506865, "lon": -116.9760516}, {"type": "node", "id": 4966862524, "lat": 44.0507183, "lon": -116.9760785}, {"type": "node", "id": 4966862525, "lat": 44.0507433, "lon": -116.9761133}, {"type": "node", "id": 4966862526, "lat": 44.0507713, "lon": -116.9761603}, {"type": "node", "id": 4966862527, "lat": 44.0507954, "lon": -116.9762166}, {"type": "node", "id": 4966862528, "lat": 44.0508098, "lon": -116.9762877}, {"type": "node", "id": 4966862529, "lat": 44.0508231, "lon": -116.9763976}, {"type": "node", "id": 4966862530, "lat": 44.0508976, "lon": -116.9760811}, {"type": "node", "id": 4966862531, "lat": 44.0508696, "lon": -116.9760141}, {"type": "node", "id": 4966862532, "lat": 44.0509158, "lon": -116.9761965}, {"type": "node", "id": 4967101895, "lat": 44.0476616, "lon": -116.976366}, {"type": "node", "id": 4967101902, "lat": 44.0464146, "lon": -116.9738673}, {"type": "node", "id": 4967101903, "lat": 44.0466804, "lon": -116.974239}, {"type": "node", "id": 4967101904, "lat": 44.0470689, "lon": -116.9747966}, {"type": "node", "id": 4967101905, "lat": 44.0473306, "lon": -116.975303}, {"type": "node", "id": 4967101906, "lat": 44.0474784, "lon": -116.9768954}, {"type": "node", "id": 4967101907, "lat": 44.047546, "lon": -116.9769038}, {"type": "node", "id": 4967101908, "lat": 44.047621, "lon": -116.9768924}, {"type": "node", "id": 4967101909, "lat": 44.0476783, "lon": -116.9769076}, {"type": "node", "id": 4967101910, "lat": 44.0477369, "lon": -116.9769493}, {"type": "node", "id": 4967101911, "lat": 44.0477846, "lon": -116.9769986}, {"type": "node", "id": 4967101912, "lat": 44.0478187, "lon": -116.9770782}, {"type": "node", "id": 4967101913, "lat": 44.0478541, "lon": -116.9771617}, {"type": "node", "id": 4967101914, "lat": 44.0479073, "lon": -116.9772831}, {"type": "node", "id": 4967101915, "lat": 44.0479673, "lon": -116.9773817}, {"type": "node", "id": 4967101916, "lat": 44.0480313, "lon": -116.9774614}, {"type": "node", "id": 4967101917, "lat": 44.0481104, "lon": -116.9775221}, {"type": "node", "id": 4967101918, "lat": 44.0479482, "lon": -116.9772565}, {"type": "node", "id": 4967101919, "lat": 44.048, "lon": -116.9773457}, {"type": "node", "id": 4967101920, "lat": 44.0480981, "lon": -116.9774614}, {"type": "node", "id": 4967101921, "lat": 44.0492309, "lon": -116.9779583}, {"type": "node", "id": 4967101922, "lat": 44.0496154, "lon": -116.9782086}, {"type": "node", "id": 5006303078, "lat": 44.0250451, "lon": -116.9469815}, {"type": "node", "id": 5006303079, "lat": 44.0249792, "lon": -116.9469449}, {"type": "node", "id": 5006303080, "lat": 44.0249315, "lon": -116.9469165}, {"type": "node", "id": 5006303081, "lat": 44.0248974, "lon": -116.9468786, "tags": {"crossing": "traffic_signals", "highway": "crossing"}}, {"type": "node", "id": 5006303082, "lat": 44.0248756, "lon": -116.9468311}, {"type": "node", "id": 5006303083, "lat": 44.0248633, "lon": -116.9467951}, {"type": "node", "id": 5006303084, "lat": 44.0248606, "lon": -116.9467041}, {"type": "node", "id": 5006303085, "lat": 44.0248619, "lon": -116.9453764}, {"type": "node", "id": 5006303086, "lat": 44.0248071, "lon": -116.9450009}, {"type": "node", "id": 5006303087, "lat": 44.0254579, "lon": -116.9471877}, {"type": "node", "id": 5006303088, "lat": 44.0249683, "lon": -116.9471801}, {"type": "node", "id": 5006303089, "lat": 44.0248715, "lon": -116.9472901}, {"type": "node", "id": 5006303090, "lat": 44.0248265, "lon": -116.947421}, {"type": "node", "id": 5006303091, "lat": 44.0271138, "lon": -116.9493556}, {"type": "node", "id": 5006303092, "lat": 44.0273607, "lon": -116.949589}, {"type": "node", "id": 5006303093, "lat": 44.0289015, "lon": -116.9509435}, {"type": "node", "id": 5006303094, "lat": 44.0285824, "lon": -116.9508362}, {"type": "node", "id": 5006303095, "lat": 44.0280829, "lon": -116.9506873}, {"type": "node", "id": 5006303096, "lat": 44.0272912, "lon": -116.9504271}, {"type": "node", "id": 5006303097, "lat": 44.0265661, "lon": -116.9502018}, {"type": "node", "id": 5006303098, "lat": 44.0259982, "lon": -116.9500999}, {"type": "node", "id": 5006303099, "lat": 44.0257918, "lon": -116.9500865}, {"type": "node", "id": 5006303100, "lat": 44.0254134, "lon": -116.9501184}, {"type": "node", "id": 5006303101, "lat": 44.0250132, "lon": -116.9502984}, {"type": "node", "id": 5008530668, "lat": 44.0176535, "lon": -116.9454969}, {"type": "node", "id": 5008530669, "lat": 44.0174339, "lon": -116.9453651}, {"type": "node", "id": 5008530670, "lat": 44.0173493, "lon": -116.9452987}, {"type": "node", "id": 5008530671, "lat": 44.0172593, "lon": -116.9452209}, {"type": "node", "id": 5009477447, "lat": 44.0258738, "lon": -116.9473925}, {"type": "node", "id": 5009477448, "lat": 44.0260279, "lon": -116.9475898}, {"type": "node", "id": 5009477449, "lat": 44.0258397, "lon": -116.9487031}, {"type": "node", "id": 5009477450, "lat": 44.0253706, "lon": -116.9487391}, {"type": "node", "id": 5009477488, "lat": 44.0245816, "lon": -116.947157, "tags": {"crossing": "traffic_signals", "highway": "crossing"}}, {"type": "node", "id": 5009477491, "lat": 44.0248775, "lon": -116.9468352, "tags": {"crossing": "traffic_signals", "highway": "crossing"}}, {"type": "node", "id": 5009477492, "lat": 44.0248811, "lon": -116.9470021, "tags": {"crossing": "traffic_signals", "highway": "crossing"}}, {"type": "node", "id": 5025017804, "lat": 44.0336955, "lon": -116.9540212}, {"type": "node", "id": 5025017805, "lat": 44.0334583, "lon": -116.9541236}, {"type": "node", "id": 5025017806, "lat": 44.0349854, "lon": -116.9562326}, {"type": "node", "id": 5025017807, "lat": 44.0348464, "lon": -116.9564754}, {"type": "node", "id": 5025017808, "lat": 44.0321029, "lon": -116.952227}, {"type": "node", "id": 5025017809, "lat": 44.0329483, "lon": -116.9530729}, {"type": "node", "id": 5025017810, "lat": 44.033341, "lon": -116.9535319}, {"type": "node", "id": 5025017811, "lat": 44.0302206, "lon": -116.9514048}, {"type": "node", "id": 5025017812, "lat": 44.0306989, "lon": -116.9516408}, {"type": "node", "id": 5025017813, "lat": 44.031263, "lon": -116.9519842}, {"type": "node", "id": 5025017814, "lat": 44.0319393, "lon": -116.9525077}, {"type": "node", "id": 5025017815, "lat": 44.0324084, "lon": -116.9529401}, {"type": "node", "id": 5025806645, "lat": 44.0269248, "lon": -116.9490954}, {"type": "node", "id": 5025806646, "lat": 44.0282362, "lon": -116.950525}, {"type": "node", "id": 5025806647, "lat": 44.0298446, "lon": -116.951209}, {"type": "node", "id": 5026277611, "lat": 44.0249106, "lon": -116.9503721, "tags": {"crossing": "traffic_signals", "highway": "crossing"}}, {"type": "node", "id": 5026277614, "lat": 44.0246301, "lon": -116.9503228, "tags": {"crossing": "traffic_signals", "highway": "crossing"}}, {"type": "node", "id": 5026277615, "lat": 44.0246096, "lon": -116.9505455, "tags": {"crossing": "traffic_signals", "highway": "crossing"}}, {"type": "node", "id": 5034004310, "lat": 44.0238909, "lon": -116.9494655}, {"type": "node", "id": 5034004311, "lat": 44.0243492, "lon": -116.9504252}, {"type": "node", "id": 5034004312, "lat": 44.0245605, "lon": -116.9503778}, {"type": "node", "id": 5034004313, "lat": 44.022867, "lon": -116.9485804}, {"type": "node", "id": 5034004314, "lat": 44.0219625, "lon": -116.9479944}, {"type": "node", "id": 5034004315, "lat": 44.0223733, "lon": -116.948213}, {"type": "node", "id": 5034004316, "lat": 44.0231708, "lon": -116.9489533}, {"type": "node", "id": 5034004317, "lat": 44.0237841, "lon": -116.9501308}, {"type": "node", "id": 5034004318, "lat": 44.0241207, "lon": -116.9505049}, {"type": "node", "id": 5034004319, "lat": 44.0241959, "lon": -116.9505438}, {"type": "node", "id": 5034004320, "lat": 44.0252458, "lon": -116.9501715}, {"type": "node", "id": 5034004321, "lat": 44.025515, "lon": -116.9500997}, {"type": "node", "id": 5942859290, "lat": 43.9738449, "lon": -116.9175696}, {"type": "node", "id": 5942859473, "lat": 43.9740219, "lon": -116.9172677}, {"type": "way", "id": 5125749, "nodes": [765981301, 35088105, 34842092, 34875433, 765981320, 765981324, 35013828, 765981331, 5009477488, 1306389685, 1306389683], "tags": {"bicycle": "yes", "destination": "Fruitland;Payette", "destination:ref": "US 30 East", "highway": "motorway_link", "oneway": "yes", "tiger:cfcc": "A63", "tiger:name_base": "Exit"}}, {"type": "way", "id": 5125983, "nodes": [34928047, 34835646, 34871615, 34899186, 35015286, 35007189, 34997478, 34885614, 766012047], "tags": {"bicycle": "yes", "highway": "motorway_link", "oneway": "yes", "tiger:cfcc": "A63", "tiger:name_base": "Exit", "tiger:reviewed": "no", "tiger:source": "tiger_import_dch_v0.6_20070808", "tiger:tlid": "138612542"}}, {"type": "way", "id": 5126326, "nodes": [766013455, 5006303093, 5006303094, 5006303095, 5006303096, 5006303097, 34891995, 5006303098, 5006303099, 35066297, 5034004321, 5006303100, 5034004320, 765981046, 5006303101, 5026277611, 1306389694, 765981043], "tags": {"bicycle": "yes", "destination": "Ontario;T.V.C.C.", "destination:ref": "US 30 BUS", "highway": "motorway_link", "oneway": "yes", "tiger:cfcc": "A63", "tiger:name_base": "Exit"}}, {"type": "way", "id": 5126480, "nodes": [766012085, 766012088, 766012089, 35059287, 34844971, 34839710, 766012094, 34928047], "tags": {"bicycle": "yes", "destination:street": "Stanton Boulevard", "highway": "motorway_link", "oneway": "yes", "tiger:cfcc": "A63", "tiger:name_base": "Exit"}}, {"type": "way", "id": 5126888, "nodes": [1306389683, 5009477492, 765981050, 5006303078, 3997842189, 3997842190, 3997842198, 765981052, 3997842197, 34850377, 3997842196, 3997842195, 3997842194, 34905131, 35055573, 766013656, 5025806645, 5006303091, 766013657, 5006303092, 766013658, 766012981], "tags": {"bicycle": "yes", "highway": "motorway_link", "lanes": "1", "oneway": "yes", "ref": "US 30", "tiger:cfcc": "A63", "tiger:name_base": "Exit"}}, {"type": "way", "id": 5127926, "nodes": [765967802, 34946694, 34995956, 3997917517, 3997917518, 35015880, 3997917519, 3997917520, 34952598], "tags": {"bicycle": "yes", "destination": "Rest Area", "highway": "motorway_link", "oneway": "yes", "tiger:cfcc": "A41"}}, {"type": "way", "id": 5128411, "nodes": [765981114, 765981120, 765981127, 5009477450, 765981131, 34839783, 5009477449, 34835710, 34853405, 34845051, 3997842193, 34861945, 3997842192, 34856907, 5009477448, 34869846, 5009477447, 34863404, 3997842191, 34850094, 5006303087, 3997842188, 3997842187, 5006303088, 766013935, 5006303089, 5006303090, 1306389687], "tags": {"bicycle": "yes", "destination": "Ontario", "destination:ref": "US 30 BUS", "highway": "motorway_link", "oneway": "yes", "tiger:cfcc": "A63", "tiger:name_base": "Exit"}}, {"type": "way", "id": 5128844, "nodes": [2740906795, 35022245, 35048129, 35038878, 35064500, 2740906784, 2740906782, 2740906779, 2740906781, 34945480, 35079326, 766012305, 766012306, 766012308], "tags": {"bicycle": "yes", "highway": "motorway_link", "oneway": "yes", "tiger:cfcc": "A63", "tiger:name_base": "Exit", "tiger:reviewed": "no"}}, {"type": "way", "id": 5129130, "nodes": [766012583, 766012587, 34900064, 34903920, 4967101922, 34942462, 4967101921, 34951694, 34999109, 3996647195, 4967101920, 3996647196, 4967101919, 4967101918, 35011619, 35019910, 34842824], "tags": {"bicycle": "yes", "destination": "Ontario;Vale", "destination:ref": "OR 201", "destination:ref:to": "US 20;US 26", "highway": "motorway_link", "oneway": "yes", "tiger:cfcc": "A63", "tiger:name_base": "Exit", "tiger:reviewed": "no"}}, {"type": "way", "id": 5129396, "nodes": [765981043, 5026277615, 765981070, 5034004319, 5034004318, 765981071, 765981072, 765981073, 5034004317, 34875756, 765981075, 5034004316, 765981076, 5034004313, 765981077, 765981078, 5034004315, 5034004314, 765967844], "tags": {"bicycle": "yes", "highway": "motorway_link", "oneway": "yes", "tiger:cfcc": "A63", "tiger:name_base": "Exit"}}, {"type": "way", "id": 13902222, "nodes": [130983528, 130983531, 130983534, 130983537, 130983541, 130983543, 130983545, 130983547, 130983550, 130983556, 130983561], "tags": {"bicycle": "yes", "destination": "Fruitland;Payette", "destination:ref": "US 95", "highway": "motorway_link", "oneway": "yes", "tiger:cfcc": "A63", "tiger:county": "Payette, ID", "tiger:reviewed": "no"}}, {"type": "way", "id": 13902995, "nodes": [131002502, 131002505, 3356376727], "tags": {"bicycle": "yes", "destination": "Rest Area", "highway": "motorway_link", "oneway": "yes", "tiger:cfcc": "A64", "tiger:county": "Payette, ID", "tiger:reviewed": "no"}}, {"type": "way", "id": 13903902, "nodes": [131019772, 131019769, 131019766, 131019763, 131019760, 131019758, 131019755, 131019751, 131019748, 131019745], "tags": {"bicycle": "yes", "destination": "Payette;Parma", "destination:ref": "US 95", "highway": "motorway_link", "oneway": "yes", "tiger:cfcc": "A63", "tiger:county": "Payette, ID", "tiger:reviewed": "no"}}, {"type": "way", "id": 13905457, "nodes": [34928230, 2825150789, 2825150791, 131055979], "tags": {"bicycle": "yes", "bridge": "yes", "hgv": "designated", "highway": "motorway", "lanes": "2", "layer": "2", "oneway": "yes", "ref": "I 84", "surface": "asphalt"}}, {"type": "way", "id": 23989837, "nodes": [131056459, 765967800, 765967802], "tags": {"alt_name": "Vietnam Veterans Memorial Highway", "bicycle": "yes", "embankment": "yes", "hgv": "designated", "highway": "motorway", "lanes": "2", "name": "Old Oregon Trail Highway", "oneway": "yes", "ref": "I 84", "surface": "asphalt"}}, {"type": "way", "id": 23989838, "nodes": [131056478, 131056477, 131056471], "tags": {"bicycle": "yes", "hgv": "designated", "highway": "motorway", "lanes": "2", "oneway": "yes", "ref": "I 84", "surface": "asphalt", "tiger:cfcc": "A15", "tiger:county": "Payette, ID", "tiger:name_base": "I-84", "tiger:reviewed": "no"}}, {"type": "way", "id": 23989839, "nodes": [260099965, 131055993, 131002502, 131055996, 1735849183, 131056002, 131002517, 131056007, 131056010, 131056014, 131056017, 131056021, 1735849024], "tags": {"bicycle": "yes", "hgv": "designated", "highway": "motorway", "lanes": "2", "oneway": "yes", "ref": "I 84", "tiger:cfcc": "A15", "tiger:county": "Payette, ID", "tiger:name_base": "I-84", "tiger:name_base_1": "United States Highway 30", "tiger:reviewed": "no", "tiger:separated": "yes", "tiger:source": "tiger_import_dch_v0.6_20070809", "tiger:tlid": "141413005:141413001:141412995:141421853:141421854:141413283:141413286:141423489:141413289:141413217:141413218:141413370:141413106:141423507:141423508:141423490:141411647:141426455:141426457:141426458:141421461:141421462:141421459:141425179:141425181:14142", "tiger:upload_uuid": "bulk_upload.pl-62561baa-4ee5-49e5-8660-d48e6fc6bf84"}}, {"type": "way", "id": 39037116, "nodes": [131055979, 1735849068, 1735849127], "tags": {"bicycle": "yes", "embankment": "yes", "hgv": "designated", "highway": "motorway", "lanes": "2", "oneway": "yes", "ref": "I 84", "surface": "asphalt", "tiger:cfcc": "A15", "tiger:county": "Payette, ID", "tiger:name_base": "I-84", "tiger:name_base_1": "United States Highway 30", "tiger:reviewed": "no"}}, {"type": "way", "id": 39037117, "nodes": [131056468, 2825150792, 2825150790, 131056459], "tags": {"bicycle": "yes", "bridge": "yes", "hgv": "designated", "highway": "motorway", "lanes": "2", "layer": "2", "oneway": "yes", "ref": "I 84", "surface": "asphalt"}}, {"type": "way", "id": 51758477, "nodes": [131014842, 131056695, 131056694, 131056693, 131056692, 131014877, 131056691, 131056689, 131056687, 131056685, 131056683, 131056681, 131056678, 131056675, 131056672, 131056669, 131056666, 131056664, 131056662, 131056659, 131056657, 131056655, 131056652, 131056649, 131056646, 131056642, 131056639, 131056636, 131056633, 131056630, 131056627, 131056624, 131056621, 131056619, 131056615, 131056611, 131056600, 131056597, 131056594, 131056592, 131056590, 131056587, 131056583, 131056580, 131056577, 131056575, 131056569, 131056566, 131056563, 131056559, 131056555, 131056549, 130983528, 131056547, 131056545, 131056541, 131056539, 5942859473, 130983566, 131056535, 130982611, 131056533, 1735849117], "tags": {"bicycle": "yes", "hgv": "designated", "highway": "motorway", "lanes": "2", "maxspeed": "70 mph", "name": "I-84", "oneway": "yes", "ref": "I 84", "tiger:cfcc": "A15", "tiger:county": "Payette, ID", "tiger:name_base": "I-84", "tiger:reviewed": "no"}}, {"type": "way", "id": 51758489, "nodes": [765981080, 765981081, 660561699, 3997842186, 660561695, 3997842185, 34882899, 5034004310, 34863238, 34858622, 3997842182, 3997842183, 34834333, 3997842184, 34828478, 5034004311, 35052434, 5034004312, 5026277614, 1306389690], "tags": {"bicycle": "yes", "destination": "Fruitland;Payette", "destination:ref": "US 30 East", "highway": "motorway_link", "lanes": "1", "oneway": "yes", "ref": "US 30", "tiger:cfcc": "A63", "tiger:name_base": "Exit"}}, {"type": "way", "id": 61323463, "nodes": [34999877, 765981150, 765981152, 5008530671, 5008530670, 5008530669, 765981153, 5008530668, 765981155, 765981156], "tags": {"bicycle": "yes", "highway": "motorway_link", "oneway": "yes"}}, {"type": "way", "id": 61478890, "nodes": [765981080, 765967861, 765967845, 765967844, 765967833, 765967822, 765967821, 765967820], "tags": {"alt_name": "Vietnam Veterans Memorial Highway", "bicycle": "yes", "hgv": "designated", "highway": "motorway", "lanes": "2", "name": "Old Oregon Trail Highway", "oneway": "yes", "ref": "I 84", "surface": "asphalt"}}, {"type": "way", "id": 61478896, "nodes": [766012981, 766012982, 766012983, 766012984, 766012985, 5025017808, 766012986, 5025017809, 5025017810, 5025017804, 766012988], "tags": {"alt_name": "Vietnam Veterans Memorial Highway", "bicycle": "yes", "hgv": "designated", "highway": "motorway", "lanes": "2", "name": "Old Oregon Trail Highway", "oneway": "yes", "ref": "I 84;US 30"}}, {"type": "way", "id": 92362829, "nodes": [1072088672, 766013296, 766013297, 766013298, 766013299, 766013300, 766013301, 766013302, 766013303, 766013304, 766013305, 766048139, 766013310, 766013311, 766013313, 766013314, 766013316, 766013317, 766013319, 766013320, 766013322, 766017936, 766017937, 766013324, 766017938, 766013326, 766013327, 766013328, 766013329, 766013330, 766013331, 766013332, 766013334, 766013335, 766013337, 766013338, 766013340, 766013342, 766013344, 766013347, 1072092921], "tags": {"alt_name": "Vietnam Veterans Memorial Highway", "bicycle": "yes", "hgv": "designated", "highway": "motorway", "lanes": "2", "name": "Old Oregon Trail Highway", "oneway": "yes", "ref": "I 84;US 30"}}, {"type": "way", "id": 92363284, "nodes": [1072092923, 766013025, 766013026, 766013027, 766013029, 766013030, 766013032, 766013034, 766013035, 766013036, 766013037, 766013039, 766013040, 766013041, 766013042, 766013043, 766017840, 766013045, 766017843, 766017845, 766013047, 766013049, 766013050, 766013053, 766013054, 766013055, 766013056, 766013058, 766013059, 766047576, 766013062, 766013064, 766013068, 766013069, 766013070, 766013071, 766013072, 766013073, 766013074, 766013075, 1072088671], "tags": {"alt_name": "Vietnam Veterans Memorial Highway", "bicycle": "yes", "hgv": "designated", "highway": "motorway", "lanes": "2", "name": "Old Oregon Trail Highway", "oneway": "yes", "ref": "I 84;US 30"}}, {"type": "way", "id": 92363286, "nodes": [1072092925, 1072092923], "tags": {"alt_name": "Vietnam Veterans Memorial Highway", "bicycle": "yes", "bridge": "yes", "hgv": "designated", "highway": "motorway", "lanes": "2", "layer": "1", "name": "Old Oregon Trail Highway", "oneway": "yes", "ref": "I 84;US 30"}}, {"type": "way", "id": 92363289, "nodes": [1072092921, 1072092927], "tags": {"alt_name": "Vietnam Veterans Memorial Highway", "bicycle": "yes", "bridge": "yes", "hgv": "designated", "highway": "motorway", "lanes": "2", "layer": "1", "name": "Old Oregon Trail Highway", "oneway": "yes", "ref": "I 84;US 30"}}, {"type": "way", "id": 92363293, "nodes": [1072092927, 766013349, 766013350, 766012085, 766013352, 766012047, 766013354, 1072097055], "tags": {"alt_name": "Vietnam Veterans Memorial Highway", "bicycle": "yes", "hgv": "designated", "highway": "motorway", "lanes": "2", "name": "Old Oregon Trail Highway", "oneway": "yes", "ref": "I 84;US 30"}}, {"type": "way", "id": 92363572, "nodes": [766012370, 766012369, 766012367, 766012364, 766012360, 2740906772, 34890446, 766012354, 2740906791, 2740906795], "tags": {"bicycle": "yes", "destination:street": "Stanton Boulevard", "highway": "motorway_link", "oneway": "yes"}}, {"type": "way", "id": 92363767, "nodes": [766013357, 766013360, 766013363, 766013372, 766013373, 766013374, 766013376, 766013377, 766013379, 766013382, 766013384, 766013389, 766013391, 766013396, 3996647201], "tags": {"alt_name": "Vietnam Veterans Memorial Highway", "bicycle": "yes", "hgv": "designated", "highway": "motorway", "lanes": "2", "name": "Old Oregon Trail Highway", "oneway": "yes", "ref": "I 84;US 30"}}, {"type": "way", "id": 92363770, "nodes": [766013020, 1072097053], "tags": {"alt_name": "Vietnam Veterans Memorial Highway", "bicycle": "yes", "bridge": "yes", "hgv": "designated", "highway": "motorway", "lanes": "2", "layer": "1", "name": "Old Oregon Trail Highway", "oneway": "yes", "ref": "I 84;US 30"}}, {"type": "way", "id": 92363772, "nodes": [1072097053, 766012370, 766013021, 766012308, 766013022, 766013023, 766013024, 1072092925], "tags": {"alt_name": "Vietnam Veterans Memorial Highway", "bicycle": "yes", "hgv": "designated", "highway": "motorway", "lanes": "2", "name": "Old Oregon Trail Highway", "oneway": "yes", "ref": "I 84;US 30"}}, {"type": "way", "id": 92363773, "nodes": [1072097055, 766013357], "tags": {"alt_name": "Vietnam Veterans Memorial Highway", "bicycle": "yes", "bridge": "yes", "hgv": "designated", "highway": "motorway", "lanes": "2", "layer": "1", "name": "Old Oregon Trail Highway", "oneway": "yes", "ref": "I 84;US 30"}}, {"type": "way", "id": 92365373, "nodes": [35026833, 4966862531, 4966862530, 4966862532, 34886124, 4966862518, 34889478, 4966862517, 34893818, 34895118, 3996647199, 34899497, 766012971], "tags": {"bicycle": "yes", "highway": "motorway_link", "oneway": "yes", "tiger:cfcc": "A63", "tiger:name_base": "Exit", "tiger:reviewed": "no"}}, {"type": "way", "id": 92365644, "nodes": [766013002, 4966125929, 4966125930, 1072117335, 4966125931, 1072117334, 3996647198, 4966125932, 1072117330, 4966125933, 1072117325, 1072117331, 4966125934, 1072117320, 4966862529, 35026833], "tags": {"bicycle": "yes", "destination": "Weiser;Vale", "destination:ref": "OR 201", "destination:ref:to": "US 20;US 26", "highway": "motorway_link", "oneway": "yes"}}, {"type": "way", "id": 92367262, "nodes": [766012989, 5025017806, 766012990], "tags": {"alt_name": "Vietnam Veterans Memorial Highway", "bicycle": "yes", "embankment": "yes", "hgv": "designated", "highway": "motorway", "lanes": "2", "name": "Old Oregon Trail Highway", "oneway": "yes", "ref": "I 84;US 30"}}, {"type": "way", "id": 92367263, "nodes": [766012988, 766012989], "tags": {"alt_name": "Vietnam Veterans Memorial Highway", "bicycle": "yes", "bridge": "yes", "hgv": "designated", "highway": "motorway", "lanes": "2", "layer": "1", "name": "Old Oregon Trail Highway", "oneway": "yes", "ref": "I 84;US 30"}}, {"type": "way", "id": 92367264, "nodes": [766013433, 766013436], "tags": {"alt_name": "Vietnam Veterans Memorial Highway", "bicycle": "yes", "bridge": "yes", "hgv": "designated", "highway": "motorway", "lanes": "2", "layer": "1", "name": "Old Oregon Trail Highway", "oneway": "yes", "ref": "I 84;US 30"}}, {"type": "way", "id": 92367265, "nodes": [766013430, 5025017807, 766013433], "tags": {"alt_name": "Vietnam Veterans Memorial Highway", "bicycle": "yes", "embankment": "yes", "hgv": "designated", "highway": "motorway", "lanes": "2", "name": "Old Oregon Trail Highway", "oneway": "yes", "ref": "I 84;US 30"}}, {"type": "way", "id": 92367266, "nodes": [766012990, 1072148252], "tags": {"alt_name": "Vietnam Veterans Memorial Highway", "bicycle": "yes", "bridge": "yes", "hgv": "designated", "highway": "motorway", "lanes": "2", "layer": "1", "name": "Old Oregon Trail Highway", "oneway": "yes", "ref": "I 84;US 30"}}, {"type": "way", "id": 92367267, "nodes": [1072148252, 766012991, 766012992, 766012995], "tags": {"alt_name": "Vietnam Veterans Memorial Highway", "bicycle": "yes", "embankment": "yes", "hgv": "designated", "highway": "motorway", "lanes": "2", "name": "Old Oregon Trail Highway", "oneway": "yes", "ref": "I 84;US 30"}}, {"type": "way", "id": 92367268, "nodes": [1072148253, 766013430], "tags": {"alt_name": "Vietnam Veterans Memorial Highway", "bicycle": "yes", "bridge": "yes", "hgv": "designated", "highway": "motorway", "lanes": "2", "layer": "1", "name": "Old Oregon Trail Highway", "oneway": "yes", "ref": "I 84;US 30"}}, {"type": "way", "id": 92367269, "nodes": [766013436, 5025017805, 766013439, 5025017815, 5025017814, 766013445, 5025017813, 766013447, 5025017812, 5025017811, 5025806647, 766013455, 5025806646, 765981080], "tags": {"alt_name": "Vietnam Veterans Memorial Highway", "bicycle": "yes", "hgv": "designated", "highway": "motorway", "lanes": "2", "name": "Old Oregon Trail Highway", "oneway": "yes", "ref": "I 84;US 30"}}, {"type": "way", "id": 161609902, "nodes": [1735849117, 1735849119], "tags": {"bicycle": "yes", "bridge": "yes", "hgv": "designated", "highway": "motorway", "lanes": "2", "layer": "1", "oneway": "yes", "ref": "I 84", "tiger:cfcc": "A15", "tiger:county": "Payette, ID", "tiger:name_base": "I-84", "tiger:reviewed": "no", "tiger:separated": "yes", "tiger:source": "tiger_import_dch_v0.6_20070809", "tiger:tlid": "141431941:141428950:141431915:141431914:141428878:141428879:141428880:141428881:141428882:141428883:141428884:141428885", "tiger:upload_uuid": "bulk_upload.pl-62561baa-4ee5-49e5-8660-d48e6fc6bf84"}}, {"type": "way", "id": 161609919, "nodes": [1735849024, 1735849032], "tags": {"bicycle": "yes", "bridge": "yes", "hgv": "designated", "highway": "motorway", "lanes": "2", "layer": "1", "oneway": "yes", "ref": "I 84", "tiger:cfcc": "A15", "tiger:county": "Payette, ID", "tiger:name_base": "I-84", "tiger:name_base_1": "United States Highway 30", "tiger:reviewed": "no", "tiger:separated": "yes", "tiger:source": "tiger_import_dch_v0.6_20070809", "tiger:tlid": "141413005:141413001:141412995:141421853:141421854:141413283:141413286:141423489:141413289:141413217:141413218:141413370:141413106:141423507:141423508:141423490:141411647:141426455:141426457:141426458:141421461:141421462:141421459:141425179:141425181:14142", "tiger:upload_uuid": "bulk_upload.pl-62561baa-4ee5-49e5-8660-d48e6fc6bf84"}}, {"type": "way", "id": 161609947, "nodes": [1735849032, 131056024, 1735849090, 131056027, 131056030, 5942859290, 131056033, 131019772, 131056036, 131056041, 131056045, 131019736, 131056049, 131056054, 1735849197, 131056056, 131056058, 131056060, 131056062, 131056064, 131056066, 131056069, 131056073, 131056076, 131056079, 131056082, 131056085, 131056099, 130945876, 131056102, 131056105, 131056108, 131056111, 131056115, 131056118, 131056121, 131056124, 131056126, 131056128, 131056130, 131056132, 131056135, 131056136, 131056138, 131056140, 131056143, 131056146, 131056149, 131056151, 131056154, 131056156, 131056158, 131056160, 131056163, 131056166, 131056169, 131056173, 131056176, 131023419, 131056179, 131056182, 131056185, 130986170, 1895589750], "tags": {"bicycle": "yes", "hgv": "designated", "highway": "motorway", "lanes": "2", "maxspeed": "70 mph", "name": "I-84", "oneway": "yes", "ref": "I 84", "tiger:cfcc": "A15", "tiger:county": "Payette, ID", "tiger:name_base": "I-84", "tiger:name_base_1": "United States Highway 30", "tiger:reviewed": "no"}}, {"type": "way", "id": 161609962, "nodes": [1735849119, 131056529, 131056525, 1735849028, 131056517, 131056501, 131056498, 131056491, 131056488, 131056482, 1735849124, 131056478], "tags": {"bicycle": "yes", "hgv": "designated", "highway": "motorway", "lanes": "2", "oneway": "yes", "ref": "I 84", "tiger:cfcc": "A15", "tiger:county": "Payette, ID", "tiger:name_base": "I-84", "tiger:reviewed": "no", "tiger:separated": "yes", "tiger:source": "tiger_import_dch_v0.6_20070809", "tiger:tlid": "141431941:141428950:141431915:141431914:141428878:141428879:141428880:141428881:141428882:141428883:141428884:141428885", "tiger:upload_uuid": "bulk_upload.pl-62561baa-4ee5-49e5-8660-d48e6fc6bf84"}}, {"type": "way", "id": 245807790, "nodes": [1735849127, 131055985, 260099965], "tags": {"bicycle": "yes", "hgv": "designated", "highway": "motorway", "lanes": "2", "oneway": "yes", "ref": "I 84", "surface": "asphalt", "tiger:cfcc": "A15", "tiger:county": "Payette, ID", "tiger:name_base": "I-84", "tiger:name_base_1": "United States Highway 30", "tiger:reviewed": "no"}}, {"type": "way", "id": 245807794, "nodes": [131056471, 1735849220, 131056468], "tags": {"bicycle": "yes", "embankment": "yes", "hgv": "designated", "highway": "motorway", "lanes": "2", "oneway": "yes", "ref": "I 84", "surface": "asphalt", "tiger:cfcc": "A15", "tiger:county": "Payette, ID", "tiger:name_base": "I-84", "tiger:reviewed": "no"}}, {"type": "way", "id": 245807797, "nodes": [765967820, 765967819, 34928230], "tags": {"alt_name": "Vietnam Veterans Memorial Highway", "bicycle": "yes", "embankment": "yes", "hgv": "designated", "highway": "motorway", "lanes": "2", "name": "Old Oregon Trail Highway", "oneway": "yes", "ref": "I 84", "surface": "asphalt"}}, {"type": "way", "id": 245807800, "nodes": [765967802, 765981156, 765981301, 765981114, 766012981], "tags": {"alt_name": "Vietnam Veterans Memorial Highway", "bicycle": "yes", "hgv": "designated", "highway": "motorway", "lanes": "2", "name": "Old Oregon Trail Highway", "oneway": "yes", "ref": "I 84", "surface": "asphalt"}}, {"type": "way", "id": 245818022, "nodes": [766012995, 766012997, 766012941, 766012999, 766013002, 766012971, 766013003], "tags": {"alt_name": "Vietnam Veterans Memorial Highway", "bicycle": "yes", "hgv": "designated", "highway": "motorway", "lanes": "2", "name": "Old Oregon Trail Highway", "oneway": "yes", "ref": "I 84;US 30"}}, {"type": "way", "id": 245818025, "nodes": [766013420, 766013423, 766013426, 1072148253], "tags": {"alt_name": "Vietnam Veterans Memorial Highway", "bicycle": "yes", "embankment": "yes", "hgv": "designated", "highway": "motorway", "lanes": "2", "name": "Old Oregon Trail Highway", "oneway": "yes", "ref": "I 84;US 30"}}, {"type": "way", "id": 268767256, "nodes": [2740906795, 34895109], "tags": {"bicycle": "yes", "highway": "motorway_link", "oneway": "no"}}, {"type": "way", "id": 328815370, "nodes": [3356376727, 3356376728, 3356376729, 3356376730], "tags": {"highway": "motorway_link", "oneway": "yes"}}, {"type": "way", "id": 333883610, "nodes": [3356376727, 131002508, 131002511, 131002512, 3356376740, 131002515, 131002517], "tags": {"bicycle": "yes", "highway": "motorway_link", "oneway": "yes", "tiger:cfcc": "A64", "tiger:county": "Payette, ID", "tiger:reviewed": "no"}}, {"type": "way", "id": 396820713, "nodes": [766013399, 766012583, 766013406, 766013411, 766012632, 766013416, 766013420], "tags": {"alt_name": "Vietnam Veterans Memorial Highway", "bicycle": "yes", "hgv": "designated", "highway": "motorway", "lanes": "2", "name": "Old Oregon Trail Highway", "oneway": "yes", "ref": "I 84;US 30"}}, {"type": "way", "id": 396820714, "nodes": [3996647200, 766013004, 766013005, 766013006, 766013008, 766013009, 766013010, 766013011, 766013012, 766013013, 766013015, 766013016, 766013017, 766013018, 766013020], "tags": {"alt_name": "Vietnam Veterans Memorial Highway", "bicycle": "yes", "hgv": "designated", "highway": "motorway", "lanes": "2", "name": "Old Oregon Trail Highway", "oneway": "yes", "ref": "I 84;US 30"}}, {"type": "way", "id": 396820715, "nodes": [3996647201, 766013399], "tags": {"alt_name": "Vietnam Veterans Memorial Highway", "bicycle": "yes", "bridge": "yes", "hgv": "designated", "highway": "motorway", "lanes": "2", "layer": "1", "name": "Old Oregon Trail Highway", "oneway": "yes", "ref": "I 84;US 30"}}, {"type": "way", "id": 420808910, "nodes": [766013003, 3996647200], "tags": {"alt_name": "Vietnam Veterans Memorial Highway", "bicycle": "yes", "bridge": "yes", "hgv": "designated", "highway": "motorway", "lanes": "2", "layer": "1", "name": "Old Oregon Trail Highway", "oneway": "yes", "ref": "I 84;US 30"}}, {"type": "way", "id": 507096257, "nodes": [4966862529, 4966862528, 4966862527, 4966862526, 4966862525, 4966862524, 4966862523, 4966862522, 4966862521, 4966862520, 4966862519], "tags": {"bicycle": "yes", "highway": "motorway_link", "oneway": "yes"}}, {"type": "way", "id": 507125963, "nodes": [3996647195, 4967101917, 4967101916, 4967101915, 4967101914, 4967101913, 4967101912, 4967101911, 4967101910, 4967101909, 4967101908, 4967101907, 4967101906], "tags": {"bicycle": "yes", "highway": "motorway_link", "oneway": "yes", "tiger:cfcc": "A63", "tiger:name_base": "Exit", "tiger:reviewed": "no"}}, {"type": "way", "id": 511889371, "nodes": [5006303086, 5006303085, 5006303084, 5006303083, 5006303082, 5009477491, 5006303081, 5006303080, 5006303079, 5006303078], "tags": {"hgv": "designated", "hgv:national_network": "yes", "highway": "motorway_link", "lanes": "1", "name": "East Idaho Avenue", "oneway": "yes", "ref": "US 30", "source:hgv:national_network": "Title 23: Highways Part 658 http://ecfr.gpoaccess.gov/cgi/t/text/text-idx?c=ecfr&rgn=div5&view=text&node=23:1.0.1.7.33&idno=23", "tiger:cfcc": "A21", "tiger:name_base": "Idaho", "tiger:name_base_1": "United States Highway 30 (Bus)", "tiger:name_direction_prefix": "E", "tiger:name_type": "Ave"}}, {"type": "way", "id": 515976562, "nodes": [34842824, 4966861906, 4967101895, 34834479, 34829324, 4967101905, 35074555, 4967101904, 35065555, 4967101903, 4967101902, 766012632], "tags": {"bicycle": "yes", "highway": "motorway_link", "oneway": "yes", "tiger:cfcc": "A63", "tiger:name_base": "Exit", "tiger:reviewed": "no"}}, {"type": "way", "id": 629491126, "nodes": [131019745, 131019742, 131019740, 131019738, 131019736], "tags": {"bicycle": "yes", "highway": "motorway_link", "oneway": "yes", "tiger:cfcc": "A63", "tiger:county": "Payette, ID", "tiger:reviewed": "no"}}, {"type": "way", "id": 629491127, "nodes": [130983561, 130933146, 130983564, 1735849195, 130983566], "tags": {"bicycle": "yes", "highway": "motorway_link", "oneway": "yes", "tiger:cfcc": "A63", "tiger:county": "Payette, ID", "tiger:reviewed": "no"}}, {"type": "way", "id": 678262751, "nodes": [2457400770, 130908199], "tags": {"highway": "trunk", "lanes": "4", "name": "Northwest 16th Street", "ref": "US 30", "surface": "asphalt", "tiger:cfcc": "A25", "tiger:county": "Payette, ID", "tiger:name_base": "16th", "tiger:name_base_1": "United States Highway 30", "tiger:name_direction_prefix": "NW", "tiger:name_type": "St"}}]}